Marvel_API_Case/Class_OOps.py
Marvel_API_Case/__init__.py
Marvel_API_Kiran-0.1.dist-info/LICENCE
Marvel_API_Kiran-0.1.dist-info/METADATA
Marvel_API_Kiran-0.1.dist-info/WHEEL
Marvel_API_Kiran-0.1.dist-info/top_level.txt
Marvel_API_Kiran-0.1.dist-info/RECORD
