Metadata-Version: 2.1
Name: Marvel-API-Kiran
Version: 0.1
Summary: Get data of characters in marvel in dataframe by taking API
Author: Kiran
License-File: LICENCE
